bifixer/__init__.py
bifixer/bifixer.py
bifixer/monofixer.py
bifixer/restorative_cleaning.py
bifixer/segmenter.py
bifixer/util.py
bifixer/detok/detok.mt
bifixer/replacements/replacements.da
bifixer/replacements/replacements.de
bifixer/replacements/replacements.en
bifixer/replacements/replacements.es
bifixer/replacements/replacements.fr
bifixer/replacements/replacements.nb
bifixer/replacements/replacements.nl
bifixer/replacements/replacements.pt
bifixer/replacements/replacements.tr
tests/test_bifixer.py
bifixer-0.8.12.dist-info/LICENSE
bifixer-0.8.12.dist-info/METADATA
bifixer-0.8.12.dist-info/WHEEL
bifixer-0.8.12.dist-info/entry_points.txt
bifixer-0.8.12.dist-info/top_level.txt
bifixer-0.8.12.dist-info/RECORD
