Metadata-Version: 2.2
Name: bifixer
Version: 0.8.12
Author-email: Prompsit Language Engineering <info@prompsit.com>
Maintainer-email: Marta Bañón <mbanon@prompsit.com>, Jaume Zaragoza <jzaragoza@prompsit.com>
License:                     GNU GENERAL PUBLIC LICENSE
Project-URL: Bifixer on GitHub, https://github.com/bitextor/bifixer
Project-URL: Prompsit Language Engineering, http://www.prompsit.com
Project-URL: Paracrawl, https://paracrawl.eu/
Project-URL: MaCoCu, https://macocu.eu
Classifier: Environment :: Console
Classifier: Intended Audience :: Science/Research
Classifier: Programming Language :: Python :: 3.8
Classifier: Programming Language :: Python :: 3.9
Classifier: Programming Language :: Python :: 3.10
Classifier: License :: OSI Approved :: GNU General Public License v3 (GPLv3)
Classifier: Operating System :: POSIX :: Linux
Classifier: Topic :: Scientific/Engineering :: Artificial Intelligence
Classifier: Topic :: Text Processing :: Linguistic
Classifier: Topic :: Software Development :: Libraries :: Python Modules
Classifier: Topic :: Text Processing :: Filters
Requires-Python: >=3.8
License-File: LICENSE
Requires-Dist: ftfy>=6
Requires-Dist: nltk>=3.9.1
Requires-Dist: pytest
Requires-Dist: regex
Requires-Dist: Unidecode
Requires-Dist: xxhash>=2.0.0
Provides-Extra: loomchild
Requires-Dist: loomchild-segment==2.0.2; extra == "loomchild"
